{
  "context": {
    "publicMode": false,
    "driveFile": "preview://data-apps/starter",
    "appVersion": "v2"
  },
  "datasets": {
    "transactions": {
      "file": "data/transactions.parquet",
      "format": "parquet"
    }
  },
  "resources": {
    "branches": [
      {
        "branchId": "AUS",
        "branchName": "Austin"
      },
      {
        "branchId": "BOS",
        "branchName": "Boston"
      },
      {
        "branchId": "CHI",
        "branchName": "Chicago"
      },
      {
        "branchId": "DEN",
        "branchName": "Denver"
      },
      {
        "branchId": "MIA",
        "branchName": "Miami"
      },
      {
        "branchId": "NSH",
        "branchName": "Nashville"
      },
      {
        "branchId": "SEA",
        "branchName": "Seattle"
      },
      {
        "branchId": "SFO",
        "branchName": "San Francisco"
      }
    ]
  }
}
